xps/__init__.py
xps/parser.py
xps/sfwagner.py
xps/xps.py
xps/data/COPYRIGHT
xps/data/sfwagner.db
xps/scatter/__init__.py
xps/scatter/imfp.py
xps-0.2.2.dist-info/METADATA
xps-0.2.2.dist-info/WHEEL
xps-0.2.2.dist-info/licenses/LICENSE
xps-0.2.2.dist-info/RECORD
