Metadata-Version: 2.1
Name: xps
Version: 0.2.2
Summary: X-Ray photonelectron spectroscopy (XPS) analysis tools
Project-URL: Homepage, https://gitlab.com/ddkn/xps
Project-URL: Bug Tracker, https://gitlab.com/ddkn/xps/-/issues
Author-email: David Kalliecharan <david@david.science>
License-File: LICENSE
Classifier: Intended Audience :: Developers
Classifier: Intended Audience :: Science/Research
Classifier: License :: OSI Approved :: ISC License (ISCL)
Classifier: Natural Language :: English
Classifier: Operating System :: OS Independent
Classifier: Programming Language :: Python :: 3
Classifier: Topic :: Scientific/Engineering :: Chemistry
Classifier: Topic :: Scientific/Engineering :: Physics
Requires-Python: >=3.7
Requires-Dist: numpy>=1.16.2
Requires-Dist: pandas
